main.py
policyengine_mcp-0.1.1.dist-info/METADATA
policyengine_mcp-0.1.1.dist-info/WHEEL
policyengine_mcp-0.1.1.dist-info/entry_points.txt
policyengine_mcp-0.1.1.dist-info/top_level.txt
policyengine_mcp-0.1.1.dist-info/RECORD
