Metadata-Version: 2.2
Name: policyengine-mcp
Version: 0.1.1
Summary: PolicyEngine Model Context Protocol server
Requires-Python: >=3.11
Requires-Dist: mcp
Requires-Dist: policyengine
